pcg_gazebo/__init__.py
pcg_gazebo/log.py
pcg_gazebo/path.py
pcg_gazebo/random.py
pcg_gazebo/transformations.py
pcg_gazebo/utils.py
pcg_gazebo/version.py
pcg_gazebo/visualization.py
pcg_gazebo/collection_managers/__init__.py
pcg_gazebo/collection_managers/_collection_manager.py
pcg_gazebo/collection_managers/assets_manager.py
pcg_gazebo/collection_managers/constraints_manager.py
pcg_gazebo/collection_managers/engine_manager.py
pcg_gazebo/collection_managers/mesh_manager.py
pcg_gazebo/collection_managers/rules_manager.py
pcg_gazebo/generators/__init__.py
pcg_gazebo/generators/_generator.py
pcg_gazebo/generators/collision_checker.py
pcg_gazebo/generators/creators.py
pcg_gazebo/generators/heightmap_generator.py
pcg_gazebo/generators/mesh.py
pcg_gazebo/generators/model_group_generator.py
pcg_gazebo/generators/occupancy.py
pcg_gazebo/generators/patterns.py
pcg_gazebo/generators/shapes.py
pcg_gazebo/generators/world_generator.py
pcg_gazebo/generators/biomes/__init__.py
pcg_gazebo/generators/biomes/biome.py
pcg_gazebo/generators/biomes/whittaker_biome.py
pcg_gazebo/generators/constraints/__init__.py
pcg_gazebo/generators/constraints/constraint.py
pcg_gazebo/generators/constraints/tangent_constraint.py
pcg_gazebo/generators/constraints/workspace_constraint.py
pcg_gazebo/generators/engines/__init__.py
pcg_gazebo/generators/engines/engine.py
pcg_gazebo/generators/engines/fixed_pose_engine.py
pcg_gazebo/generators/engines/pattern_engine.py
pcg_gazebo/generators/engines/random_pose_engine.py
pcg_gazebo/generators/item_pickers/__init__.py
pcg_gazebo/generators/item_pickers/_picker.py
pcg_gazebo/generators/item_pickers/random_picker.py
pcg_gazebo/generators/item_pickers/roulette_wheel_picker.py
pcg_gazebo/generators/item_pickers/size_picker.py
pcg_gazebo/generators/rules/__init__.py
pcg_gazebo/generators/rules/fixed_value.py
pcg_gazebo/generators/rules/from_set.py
pcg_gazebo/generators/rules/random.py
pcg_gazebo/generators/rules/rule.py
pcg_gazebo/generators/rules/uniform.py
pcg_gazebo-0.7.12.dist-info/LICENSE
pcg_gazebo-0.7.12.dist-info/METADATA
pcg_gazebo-0.7.12.dist-info/NOTICE
pcg_gazebo-0.7.12.dist-info/WHEEL
pcg_gazebo-0.7.12.dist-info/top_level.txt
pcg_gazebo-0.7.12.dist-info/RECORD
