Metadata-Version: 2.1
Name: pcg-gazebo
Version: 0.7.12
Summary: A Python package for rapid-prototyping and scripting of simulations for Gazebo
Home-page: https://github.com/boschresearch/pcg_gazebo
Author: Musa Morena Marcusso Manhaes
Author-email: musa.marcusso@de.bosch.com
Maintainer: Musa Morena Marcusso Manhaes
Maintainer-email: musa.marcusso@de.bosch.com
License: Apache-2.0
Keywords: gazebo ros simulation robotics sdf urdf robot
Platform: UNKNOWN
Classifier: License :: OSI Approved :: Apache Software License
Classifier: Programming Language :: Python :: 2.7
Classifier: Programming Language :: Python :: 3.6
Classifier: Programming Language :: Python :: 3.7
Classifier: Programming Language :: Python :: 3.8
Requires-Dist: psutil
Requires-Dist: Jinja2 (<2.11)
Requires-Dist: rospkg
Requires-Dist: progress
Requires-Dist: bokeh
Requires-Dist: scikit-image
Requires-Dist: noise
Requires-Dist: yasha
Requires-Dist: trimesh[easy] (>=3.6.4)
Requires-Dist: descartes
Requires-Dist: lxml
Requires-Dist: matplotlib
Requires-Dist: numpy (>=1.18.1)
Requires-Dist: python-fcl
Requires-Dist: triangle
Requires-Dist: networkx
Requires-Dist: pycollada (==0.6)
Requires-Dist: jsonschema
Requires-Dist: PyYAML
Requires-Dist: xmltodict
Requires-Dist: tabulate
Requires-Dist: shapely (<=1.7.0)
Provides-Extra: all
Requires-Dist: psutil ; extra == 'all'
Requires-Dist: Jinja2 (<2.11) ; extra == 'all'
Requires-Dist: lxml ; extra == 'all'
Requires-Dist: nbconvert ; extra == 'all'
Requires-Dist: rospkg ; extra == 'all'
Requires-Dist: matplotlib ; extra == 'all'
Requires-Dist: numpy (>=1.18.1) ; extra == 'all'
Requires-Dist: pytest ; extra == 'all'
Requires-Dist: python-fcl ; extra == 'all'
Requires-Dist: pytest-console-scripts ; extra == 'all'
Requires-Dist: progress ; extra == 'all'
Requires-Dist: triangle ; extra == 'all'
Requires-Dist: bokeh ; extra == 'all'
Requires-Dist: networkx ; extra == 'all'
Requires-Dist: pypandoc ; extra == 'all'
Requires-Dist: scikit-image ; extra == 'all'
Requires-Dist: pycollada (==0.6) ; extra == 'all'
Requires-Dist: jsonschema ; extra == 'all'
Requires-Dist: noise ; extra == 'all'
Requires-Dist: yasha ; extra == 'all'
Requires-Dist: PyYAML ; extra == 'all'
Requires-Dist: mkdocs-awesome-pages-plugin ; extra == 'all'
Requires-Dist: pydoc-markdown ; extra == 'all'
Requires-Dist: mkdocs-material ; extra == 'all'
Requires-Dist: trimesh[easy] (>=3.6.4) ; extra == 'all'
Requires-Dist: xmltodict ; extra == 'all'
Requires-Dist: descartes ; extra == 'all'
Requires-Dist: tabulate ; extra == 'all'
Requires-Dist: jupyterlab ; extra == 'all'
Requires-Dist: shapely (<=1.7.0) ; extra == 'all'
Provides-Extra: docs
Requires-Dist: psutil ; extra == 'docs'
Requires-Dist: Jinja2 (<2.11) ; extra == 'docs'
Requires-Dist: lxml ; extra == 'docs'
Requires-Dist: nbconvert ; extra == 'docs'
Requires-Dist: rospkg ; extra == 'docs'
Requires-Dist: matplotlib ; extra == 'docs'
Requires-Dist: numpy (>=1.18.1) ; extra == 'docs'
Requires-Dist: python-fcl ; extra == 'docs'
Requires-Dist: progress ; extra == 'docs'
Requires-Dist: triangle ; extra == 'docs'
Requires-Dist: bokeh ; extra == 'docs'
Requires-Dist: networkx ; extra == 'docs'
Requires-Dist: pypandoc ; extra == 'docs'
Requires-Dist: scikit-image ; extra == 'docs'
Requires-Dist: pycollada (==0.6) ; extra == 'docs'
Requires-Dist: jsonschema ; extra == 'docs'
Requires-Dist: noise ; extra == 'docs'
Requires-Dist: yasha ; extra == 'docs'
Requires-Dist: PyYAML ; extra == 'docs'
Requires-Dist: mkdocs-material ; extra == 'docs'
Requires-Dist: pydoc-markdown ; extra == 'docs'
Requires-Dist: trimesh[easy] (>=3.6.4) ; extra == 'docs'
Requires-Dist: xmltodict ; extra == 'docs'
Requires-Dist: descartes ; extra == 'docs'
Requires-Dist: tabulate ; extra == 'docs'
Requires-Dist: shapely (<=1.7.0) ; extra == 'docs'
Provides-Extra: examples
Requires-Dist: psutil ; extra == 'examples'
Requires-Dist: Jinja2 (<2.11) ; extra == 'examples'
Requires-Dist: lxml ; extra == 'examples'
Requires-Dist: rospkg ; extra == 'examples'
Requires-Dist: matplotlib ; extra == 'examples'
Requires-Dist: numpy (>=1.18.1) ; extra == 'examples'
Requires-Dist: python-fcl ; extra == 'examples'
Requires-Dist: progress ; extra == 'examples'
Requires-Dist: triangle ; extra == 'examples'
Requires-Dist: bokeh ; extra == 'examples'
Requires-Dist: networkx ; extra == 'examples'
Requires-Dist: scikit-image ; extra == 'examples'
Requires-Dist: pycollada (==0.6) ; extra == 'examples'
Requires-Dist: jsonschema ; extra == 'examples'
Requires-Dist: noise ; extra == 'examples'
Requires-Dist: yasha ; extra == 'examples'
Requires-Dist: PyYAML ; extra == 'examples'
Requires-Dist: trimesh[easy] (>=3.6.4) ; extra == 'examples'
Requires-Dist: xmltodict ; extra == 'examples'
Requires-Dist: descartes ; extra == 'examples'
Requires-Dist: tabulate ; extra == 'examples'
Requires-Dist: jupyterlab ; extra == 'examples'
Requires-Dist: shapely (<=1.7.0) ; extra == 'examples'
Provides-Extra: test
Requires-Dist: psutil ; extra == 'test'
Requires-Dist: Jinja2 (<2.11) ; extra == 'test'
Requires-Dist: lxml ; extra == 'test'
Requires-Dist: nbconvert ; extra == 'test'
Requires-Dist: rospkg ; extra == 'test'
Requires-Dist: matplotlib ; extra == 'test'
Requires-Dist: numpy (>=1.18.1) ; extra == 'test'
Requires-Dist: pytest ; extra == 'test'
Requires-Dist: python-fcl ; extra == 'test'
Requires-Dist: progress ; extra == 'test'
Requires-Dist: triangle ; extra == 'test'
Requires-Dist: bokeh ; extra == 'test'
Requires-Dist: networkx ; extra == 'test'
Requires-Dist: scikit-image ; extra == 'test'
Requires-Dist: pycollada (==0.6) ; extra == 'test'
Requires-Dist: jsonschema ; extra == 'test'
Requires-Dist: noise ; extra == 'test'
Requires-Dist: yasha ; extra == 'test'
Requires-Dist: PyYAML ; extra == 'test'
Requires-Dist: trimesh[easy] (>=3.6.4) ; extra == 'test'
Requires-Dist: xmltodict ; extra == 'test'
Requires-Dist: descartes ; extra == 'test'
Requires-Dist: tabulate ; extra == 'test'
Requires-Dist: shapely (<=1.7.0) ; extra == 'test'
